subscribe/__init__.py
subscribe/subscribers.py
subscribe/subscriptions.py
subscribe-0.6.3.dist-info/METADATA
subscribe-0.6.3.dist-info/WHEEL
subscribe-0.6.3.dist-info/RECORD
