Metadata-Version: 2.1
Name: subscribe
Version: 0.6.3
Summary: Library for managing subscriptions
Home-page: https://github.com/mrijken/subscribe
License: MIT
Author: Marc Rijken
Author-email: marc@rijken.org
Requires-Python: >=3.6.2,<4.0
Classifier: License :: OSI Approved :: MIT License
Classifier: Programming Language :: Python :: 3
Classifier: Programming Language :: Python :: 3.7
Classifier: Programming Language :: Python :: 3.8
Classifier: Programming Language :: Python :: 3.9
Classifier: Programming Language :: Python :: 3.10
Classifier: Programming Language :: Python :: 3.11
Classifier: Programming Language :: Python :: 3.12
Project-URL: Repository, https://github.com/mrijken/subscribe
